serobj/__init__.py
serobj/attrs.py
serobj/protocol/__init__.py
serobj/protocol/base.py
serobj/protocol/zero.py
serobj/utils/__init__.py
serobj/utils/path_to_object.py
serobj/utils/serobj_calls.py
serobj-0.0.3.dist-info/LICENSE
serobj-0.0.3.dist-info/METADATA
serobj-0.0.3.dist-info/WHEEL
serobj-0.0.3.dist-info/top_level.txt
serobj-0.0.3.dist-info/RECORD
