Metadata-Version: 2.1
Name: serobj
Version: 0.0.3
Summary: Python objects serialization
Home-page: https://github.com/serobj/serobj-python
Author: Vadim Sharay
Author-email: vadimsharay@gmail.com
Maintainer: Vadim Sharay
Maintainer-email: vadimsharay@gmail.com
License: Apache License, Version 2.0
Keywords: serialization representation format serobj syrup
Platform: UNKNOWN
Classifier: Development Status :: 3 - Alpha
Classifier: License :: OSI Approved :: Apache Software License
Classifier: Operating System :: OS Independent
Classifier: Programming Language :: Python :: 3.5
Classifier: Programming Language :: Python :: 3.6
Classifier: Programming Language :: Python :: 3.7
Classifier: Programming Language :: Python :: Implementation :: PyPy
Classifier: Intended Audience :: Developers
Classifier: Intended Audience :: System Administrators
Classifier: Topic :: Software Development :: Libraries :: Python Modules
Classifier: Topic :: Scientific/Engineering
Classifier: Topic :: System :: Distributed Computing
Classifier: Topic :: Utilities
Requires-Python: ~=3.5
Requires-Dist: cerberus (~=1.3)
Provides-Extra: dev
Requires-Dist: flake8 (~=3.7) ; extra == 'dev'
Requires-Dist: flake8-black (~=0.1) ; extra == 'dev'
Requires-Dist: black (==19.10b0) ; extra == 'dev'
Requires-Dist: pytest (~=5.4) ; extra == 'dev'
Requires-Dist: pre-commit (~=1.20) ; extra == 'dev'
